Metadata-Version: 2.1
Name: avocado-framework-plugin-runner-remote
Version: 80.0
Summary: Avocado Runner for Remote Execution
Home-page: http://avocado-framework.github.io/
Author: Avocado Developers
Author-email: avocado-devel@redhat.com
License: UNKNOWN
Platform: UNKNOWN
Requires-Dist: avocado-framework (==80.0)
Requires-Dist: Fabric3 (<2.0.0,>=1.1.4)
